scoop_python/__init__.py
scoop_python-0.1.1.dist-info/METADATA
scoop_python-0.1.1.dist-info/WHEEL
scoop_python-0.1.1.dist-info/entry_points.txt
scoop_python-0.1.1.dist-info/RECORD
